genai_toolkit/__init__.py
genai_toolkit-0.2.0.dist-info/METADATA
genai_toolkit-0.2.0.dist-info/WHEEL
genai_toolkit-0.2.0.dist-info/top_level.txt
genai_toolkit-0.2.0.dist-info/RECORD
