Metadata-Version: 2.1
Name: genai-toolkit
Version: 0.2.0
Author: Amazon Web Services
Requires-Python: >=3.12
Requires-Dist: boto3 ~=1.34.140
Provides-Extra: all
Requires-Dist: itables ~=2.1.4 ; extra == 'all'
Requires-Dist: nltk ~=3.9.1 ; extra == 'all'
Requires-Dist: pandas ~=2.2.2 ; extra == 'all'
Requires-Dist: jsonpickle ~=3.2.2 ; extra == 'all'
Requires-Dist: scikit-learn ~=1.5.1 ; extra == 'all'
Requires-Dist: boto3-stubs[bedrock-runtime,dynamodb] ~=1.35.2 ; extra == 'all'
Requires-Dist: uvicorn ~=0.30.5 ; extra == 'all'
Requires-Dist: fastapi ~=0.112.0 ; extra == 'all'
Requires-Dist: colorama ~=0.4.6 ; extra == 'all'
Requires-Dist: requests ~=2.32.3 ; extra == 'all'
Requires-Dist: tabulate ~=0.9.0 ; extra == 'all'
Provides-Extra: dev
Requires-Dist: boto3-stubs[bedrock-runtime,dynamodb] ~=1.35.2 ; extra == 'dev'
Provides-Extra: evaluate
Requires-Dist: nltk ~=3.9.1 ; extra == 'evaluate'
Requires-Dist: scikit-learn ~=1.5.1 ; extra == 'evaluate'
Provides-Extra: interactive
Requires-Dist: pandas ~=2.2.2 ; extra == 'interactive'
Requires-Dist: colorama ~=0.4.6 ; extra == 'interactive'
Requires-Dist: jsonpickle ~=3.2.2 ; extra == 'interactive'
Requires-Dist: requests ~=2.32.3 ; extra == 'interactive'
Requires-Dist: itables ~=2.1.4 ; extra == 'interactive'
Requires-Dist: tabulate ~=0.9.0 ; extra == 'interactive'
Provides-Extra: run-agent
Requires-Dist: fastapi ~=0.112.0 ; extra == 'run-agent'
Requires-Dist: uvicorn ~=0.30.5 ; extra == 'run-agent'
